ml_project_generator/__init__.py
ml_project_generator/main.py
ml_project_generator/project_creator.py
ml_project_generator/utils.py
ml_project_generator/templates/docs/README.md
ml_project_generator/templates/docs/conf.py
ml_project_generator/templates/docs/index.rst
ml_project_generator-2.0.2.dist-info/licenses/LICENSE
ml_project_generator-2.0.2.dist-info/METADATA
ml_project_generator-2.0.2.dist-info/WHEEL
ml_project_generator-2.0.2.dist-info/entry_points.txt
ml_project_generator-2.0.2.dist-info/top_level.txt
ml_project_generator-2.0.2.dist-info/RECORD
