Metadata-Version: 2.4
Name: ml-project-generator
Version: 2.0.2
Summary: A command-line tool to generate structured ML project templates with documentation and best practices
Author-email: AarambhaAnta <aarambha108@gmail.com>
License: MIT License
Project-URL: Homepage, https://github.com/AarambhaAnta/ml-project-generator
Project-URL: Documentation, https://github.com/AarambhaAnta/ml-project-generator#readme
Project-URL: Issues, https://github.com/AarambhaAnta/ml-project-generator/issues
Project-URL: Source, https://github.com/AarambhaAnta/ml-project-generator
Project-URL: Bug Tracker, https://github.com/AarambhaAnta/ml-project-generator/issues
Keywords: machine learning,project generator,template,CLI,ml,ai,deep learning,nlp,computer vision
Classifier: Development Status :: 4 - Beta
Classifier: Intended Audience :: Developers
Classifier: Topic :: Software Development :: Build Tools
Classifier: Programming Language :: Python :: 3
Classifier: Programming Language :: Python :: 3.7
Classifier: Programming Language :: Python :: 3.8
Classifier: Programming Language :: Python :: 3.9
Classifier: Programming Language :: Python :: 3.10
Classifier: License :: OSI Approved :: MIT License
Classifier: Operating System :: OS Independent
Classifier: Operating System :: MacOS :: MacOS X
Classifier: Operating System :: Microsoft :: Windows
Classifier: Operating System :: POSIX :: Linux
Requires-Python: >=3.7
License-File: LICENSE
Requires-Dist: numpy>=1.21
Requires-Dist: pandas>=1.3
Requires-Dist: scikit-learn>=1.0
Provides-Extra: deep-learning
Requires-Dist: torch>=2.0; python_version >= "3.8" and extra == "deep-learning"
Requires-Dist: torchvision>=0.15; python_version >= "3.8" and extra == "deep-learning"
Provides-Extra: nlp
Requires-Dist: transformers>=4.30; python_version >= "3.8" and extra == "nlp"
Requires-Dist: nltk>=3.8; python_version >= "3.8" and extra == "nlp"
Provides-Extra: cv
Requires-Dist: opencv-python>=4.8; python_version >= "3.8" and extra == "cv"
Dynamic: license-file
